<?xml version="1.0" encoding="UTF-8"?>
<?xml-stylesheet type="text/xsl" href="file:///Users/troyer/opt/lib/xml/ALPS.xsl"?>
<SIMULATION xmlns:xsi="http://www.w3.org/2001/XMLSchema-instance" xsi:noNamespaceSchemaLocation="http://xml.comp-phys.org/2002/10/ALPS.xsd">
  <PARAMETERS>
    <PARAMETER name="SWEEPS">500000</PARAMETER>
    <PARAMETER name="THERMALIZATION">15000</PARAMETER>
    <PARAMETER name="J">-1</PARAMETER>
    <PARAMETER name="UPDATE">cluster</PARAMETER>
    <PARAMETER name="L">60</PARAMETER>
    <PARAMETER name="LATTICE">chain lattice</PARAMETER>
    <PARAMETER name="T">1.0</PARAMETER>
    <PARAMETER name="MODEL">Ising</PARAMETER>
    <PARAMETER name="SEED">1551668846</PARAMETER>
  </PARAMETERS>
  <AVERAGES>
    <SCALAR_AVERAGE name="(beta * Energy)^2 / N">
      <COUNT>827460</COUNT>
      <MEAN method="simple">35.16701</MEAN>
      <ERROR converged="yes" method="binning">0.0272</ERROR>
      <VARIANCE method="simple">57.3</VARIANCE>
      <AUTOCORR method="binning">4.83</AUTOCORR>
      <BINNED size="1"><COUNT>827460</COUNT><MEAN method="simple">35.16701</MEAN><ERROR method="simple">0.00832</ERROR></BINNED>
      <BINNED size="2"><COUNT>413730</COUNT><MEAN method="simple">35.16701</MEAN><ERROR method="simple">0.0113</ERROR></BINNED>
      <BINNED size="4"><COUNT>206865</COUNT><MEAN method="simple">35.16701</MEAN><ERROR method="simple">0.015</ERROR></BINNED>
      <BINNED size="8"><COUNT>103432</COUNT><MEAN method="simple">35.16697</MEAN><ERROR method="simple">0.0193</ERROR></BINNED>
      <BINNED size="16"><COUNT>51716</COUNT><MEAN method="simple">35.16697</MEAN><ERROR method="simple">0.0235</ERROR></BINNED>
      <BINNED size="32"><COUNT>25858</COUNT><MEAN method="simple">35.16697</MEAN><ERROR method="simple">0.0267</ERROR></BINNED>
      <BINNED size="64"><COUNT>12929</COUNT><MEAN method="simple">35.16697</MEAN><ERROR method="simple">0.0284</ERROR></BINNED>
      <BINNED size="128"><COUNT>6464</COUNT><MEAN method="simple">35.16709</MEAN><ERROR method="simple">0.0294</ERROR></BINNED>
      <BINNED size="256"><COUNT>3232</COUNT><MEAN method="simple">35.16709</MEAN><ERROR method="simple">0.0298</ERROR></BINNED>
      <BINNED size="512"><COUNT>1616</COUNT><MEAN method="simple">35.16709</MEAN><ERROR method="simple">0.03</ERROR></BINNED>
      <BINNED size="1024"><COUNT>808</COUNT><MEAN method="simple">35.16709</MEAN><ERROR method="simple">0.0291</ERROR></BINNED>
      <BINNED size="2048"><COUNT>404</COUNT><MEAN method="simple">35.16709</MEAN><ERROR method="simple">0.0284</ERROR></BINNED>
      <BINNED size="4096"><COUNT>202</COUNT><MEAN method="simple">35.16709</MEAN><ERROR method="simple">0.0272</ERROR></BINNED>
    </SCALAR_AVERAGE>
    <VECTOR_AVERAGE name="Bond-type Energy" nvalues="1">
      <SCALAR_AVERAGE indexvalue="0">
        <COUNT>827460</COUNT>
        <MEAN method="simple">-45.65692</MEAN>
        <ERROR converged="yes" method="binning">0.0184</ERROR>
        <VARIANCE method="simple">25.5</VARIANCE>
        <AUTOCORR method="binning">5.03</AUTOCORR>
        <BINNED size="1"><COUNT>827460</COUNT><MEAN method="simple">-45.656921</MEAN><ERROR method="simple">0.00555</ERROR></BINNED>
        <BINNED size="2"><COUNT>413730</COUNT><MEAN method="simple">-45.656921</MEAN><ERROR method="simple">0.00753</ERROR></BINNED>
        <BINNED size="4"><COUNT>206865</COUNT><MEAN method="simple">-45.656921</MEAN><ERROR method="simple">0.0101</ERROR></BINNED>
        <BINNED size="8"><COUNT>103432</COUNT><MEAN method="simple">-45.656891</MEAN><ERROR method="simple">0.013</ERROR></BINNED>
        <BINNED size="16"><COUNT>51716</COUNT><MEAN method="simple">-45.656891</MEAN><ERROR method="simple">0.0158</ERROR></BINNED>
        <BINNED size="32"><COUNT>25858</COUNT><MEAN method="simple">-45.656891</MEAN><ERROR method="simple">0.018</ERROR></BINNED>
        <BINNED size="64"><COUNT>12929</COUNT><MEAN method="simple">-45.656891</MEAN><ERROR method="simple">0.0191</ERROR></BINNED>
        <BINNED size="128"><COUNT>6464</COUNT><MEAN method="simple">-45.65697</MEAN><ERROR method="simple">0.0198</ERROR></BINNED>
        <BINNED size="256"><COUNT>3232</COUNT><MEAN method="simple">-45.65697</MEAN><ERROR method="simple">0.0201</ERROR></BINNED>
        <BINNED size="512"><COUNT>1616</COUNT><MEAN method="simple">-45.65697</MEAN><ERROR method="simple">0.0202</ERROR></BINNED>
        <BINNED size="1024"><COUNT>808</COUNT><MEAN method="simple">-45.65697</MEAN><ERROR method="simple">0.0196</ERROR></BINNED>
        <BINNED size="2048"><COUNT>404</COUNT><MEAN method="simple">-45.65697</MEAN><ERROR method="simple">0.0192</ERROR></BINNED>
        <BINNED size="4096"><COUNT>202</COUNT><MEAN method="simple">-45.65697</MEAN><ERROR method="simple">0.0184</ERROR></BINNED>
      </SCALAR_AVERAGE>
    </VECTOR_AVERAGE>
    <VECTOR_AVERAGE name="Bond-type Energy Density" nvalues="1">
      <SCALAR_AVERAGE indexvalue="0">
        <COUNT>827460</COUNT>
        <MEAN method="simple">-0.7609487</MEAN>
        <ERROR converged="yes" method="binning">0.000307</ERROR>
        <VARIANCE method="simple">0.00707</VARIANCE>
        <AUTOCORR method="binning">5.03</AUTOCORR>
        <BINNED size="1"><COUNT>827460</COUNT><MEAN method="simple">-0.76094869</MEAN><ERROR method="simple">9.25e-05</ERROR></BINNED>
        <BINNED size="2"><COUNT>413730</COUNT><MEAN method="simple">-0.76094869</MEAN><ERROR method="simple">0.000126</ERROR></BINNED>
        <BINNED size="4"><COUNT>206865</COUNT><MEAN method="simple">-0.76094869</MEAN><ERROR method="simple">0.000168</ERROR></BINNED>
        <BINNED size="8"><COUNT>103432</COUNT><MEAN method="simple">-0.76094818</MEAN><ERROR method="simple">0.000216</ERROR></BINNED>
        <BINNED size="16"><COUNT>51716</COUNT><MEAN method="simple">-0.76094818</MEAN><ERROR method="simple">0.000264</ERROR></BINNED>
        <BINNED size="32"><COUNT>25858</COUNT><MEAN method="simple">-0.76094818</MEAN><ERROR method="simple">0.000299</ERROR></BINNED>
        <BINNED size="64"><COUNT>12929</COUNT><MEAN method="simple">-0.76094818</MEAN><ERROR method="simple">0.000319</ERROR></BINNED>
        <BINNED size="128"><COUNT>6464</COUNT><MEAN method="simple">-0.76094951</MEAN><ERROR method="simple">0.00033</ERROR></BINNED>
        <BINNED size="256"><COUNT>3232</COUNT><MEAN method="simple">-0.76094951</MEAN><ERROR method="simple">0.000335</ERROR></BINNED>
        <BINNED size="512"><COUNT>1616</COUNT><MEAN method="simple">-0.76094951</MEAN><ERROR method="simple">0.000336</ERROR></BINNED>
        <BINNED size="1024"><COUNT>808</COUNT><MEAN method="simple">-0.76094951</MEAN><ERROR method="simple">0.000327</ERROR></BINNED>
        <BINNED size="2048"><COUNT>404</COUNT><MEAN method="simple">-0.76094951</MEAN><ERROR method="simple">0.000321</ERROR></BINNED>
        <BINNED size="4096"><COUNT>202</COUNT><MEAN method="simple">-0.76094951</MEAN><ERROR method="simple">0.000307</ERROR></BINNED>
      </SCALAR_AVERAGE>
    </VECTOR_AVERAGE>
    <SCALAR_AVERAGE name="Cluster size">
      <COUNT>827460</COUNT>
      <MEAN method="simple">0.1231299</MEAN>
      <ERROR converged="yes" method="binning">0.00012</ERROR>
      <VARIANCE method="simple">0.00746</VARIANCE>
      <AUTOCORR method="binning">0.295</AUTOCORR>
      <BINNED size="1"><COUNT>827460</COUNT><MEAN method="simple">0.1231299</MEAN><ERROR method="simple">9.49e-05</ERROR></BINNED>
      <BINNED size="2"><COUNT>413730</COUNT><MEAN method="simple">0.1231299</MEAN><ERROR method="simple">9.84e-05</ERROR></BINNED>
      <BINNED size="4"><COUNT>206865</COUNT><MEAN method="simple">0.1231299</MEAN><ERROR method="simple">0.000103</ERROR></BINNED>
      <BINNED size="8"><COUNT>103432</COUNT><MEAN method="simple">0.1231298</MEAN><ERROR method="simple">0.00011</ERROR></BINNED>
      <BINNED size="16"><COUNT>51716</COUNT><MEAN method="simple">0.1231298</MEAN><ERROR method="simple">0.000116</ERROR></BINNED>
      <BINNED size="32"><COUNT>25858</COUNT><MEAN method="simple">0.1231298</MEAN><ERROR method="simple">0.000121</ERROR></BINNED>
      <BINNED size="64"><COUNT>12929</COUNT><MEAN method="simple">0.12313</MEAN><ERROR method="simple">0.000123</ERROR></BINNED>
      <BINNED size="128"><COUNT>6464</COUNT><MEAN method="simple">0.12313</MEAN><ERROR method="simple">0.000124</ERROR></BINNED>
      <BINNED size="256"><COUNT>3232</COUNT><MEAN method="simple">0.12313</MEAN><ERROR method="simple">0.000124</ERROR></BINNED>
      <BINNED size="512"><COUNT>1616</COUNT><MEAN method="simple">0.1231301</MEAN><ERROR method="simple">0.000123</ERROR></BINNED>
      <BINNED size="1024"><COUNT>808</COUNT><MEAN method="simple">0.1231301</MEAN><ERROR method="simple">0.000122</ERROR></BINNED>
      <BINNED size="2048"><COUNT>404</COUNT><MEAN method="simple">0.1231301</MEAN><ERROR method="simple">0.000117</ERROR></BINNED>
      <BINNED size="4096"><COUNT>202</COUNT><MEAN method="simple">0.1231301</MEAN><ERROR method="simple">0.00012</ERROR></BINNED>
    </SCALAR_AVERAGE>
    <SCALAR_AVERAGE name="Energy">
      <COUNT>827460</COUNT>
      <MEAN method="simple">-45.65692</MEAN>
      <ERROR converged="yes" method="binning">0.0184</ERROR>
      <VARIANCE method="simple">25.5</VARIANCE>
      <AUTOCORR method="binning">5.03</AUTOCORR>
      <BINNED size="1"><COUNT>827460</COUNT><MEAN method="simple">-45.65692</MEAN><ERROR method="simple">0.00555</ERROR></BINNED>
      <BINNED size="2"><COUNT>413730</COUNT><MEAN method="simple">-45.65692</MEAN><ERROR method="simple">0.00753</ERROR></BINNED>
      <BINNED size="4"><COUNT>206865</COUNT><MEAN method="simple">-45.65692</MEAN><ERROR method="simple">0.0101</ERROR></BINNED>
      <BINNED size="8"><COUNT>103432</COUNT><MEAN method="simple">-45.65689</MEAN><ERROR method="simple">0.013</ERROR></BINNED>
      <BINNED size="16"><COUNT>51716</COUNT><MEAN method="simple">-45.65689</MEAN><ERROR method="simple">0.0158</ERROR></BINNED>
      <BINNED size="32"><COUNT>25858</COUNT><MEAN method="simple">-45.65689</MEAN><ERROR method="simple">0.018</ERROR></BINNED>
      <BINNED size="64"><COUNT>12929</COUNT><MEAN method="simple">-45.65689</MEAN><ERROR method="simple">0.0191</ERROR></BINNED>
      <BINNED size="128"><COUNT>6464</COUNT><MEAN method="simple">-45.65697</MEAN><ERROR method="simple">0.0198</ERROR></BINNED>
      <BINNED size="256"><COUNT>3232</COUNT><MEAN method="simple">-45.65697</MEAN><ERROR method="simple">0.0201</ERROR></BINNED>
      <BINNED size="512"><COUNT>1616</COUNT><MEAN method="simple">-45.65697</MEAN><ERROR method="simple">0.0202</ERROR></BINNED>
      <BINNED size="1024"><COUNT>808</COUNT><MEAN method="simple">-45.65697</MEAN><ERROR method="simple">0.0196</ERROR></BINNED>
      <BINNED size="2048"><COUNT>404</COUNT><MEAN method="simple">-45.65697</MEAN><ERROR method="simple">0.0192</ERROR></BINNED>
      <BINNED size="4096"><COUNT>202</COUNT><MEAN method="simple">-45.65697</MEAN><ERROR method="simple">0.0184</ERROR></BINNED>
    </SCALAR_AVERAGE>
    <SCALAR_AVERAGE name="Energy Density">
      <COUNT>827460</COUNT>
      <MEAN method="simple">-0.7609487</MEAN>
      <ERROR converged="yes" method="binning">0.000307</ERROR>
      <VARIANCE method="simple">0.00707</VARIANCE>
      <AUTOCORR method="binning">5.03</AUTOCORR>
      <BINNED size="1"><COUNT>827460</COUNT><MEAN method="simple">-0.7609487</MEAN><ERROR method="simple">9.25e-05</ERROR></BINNED>
      <BINNED size="2"><COUNT>413730</COUNT><MEAN method="simple">-0.7609487</MEAN><ERROR method="simple">0.000126</ERROR></BINNED>
      <BINNED size="4"><COUNT>206865</COUNT><MEAN method="simple">-0.7609487</MEAN><ERROR method="simple">0.000168</ERROR></BINNED>
      <BINNED size="8"><COUNT>103432</COUNT><MEAN method="simple">-0.7609482</MEAN><ERROR method="simple">0.000216</ERROR></BINNED>
      <BINNED size="16"><COUNT>51716</COUNT><MEAN method="simple">-0.7609482</MEAN><ERROR method="simple">0.000264</ERROR></BINNED>
      <BINNED size="32"><COUNT>25858</COUNT><MEAN method="simple">-0.7609482</MEAN><ERROR method="simple">0.000299</ERROR></BINNED>
      <BINNED size="64"><COUNT>12929</COUNT><MEAN method="simple">-0.7609482</MEAN><ERROR method="simple">0.000319</ERROR></BINNED>
      <BINNED size="128"><COUNT>6464</COUNT><MEAN method="simple">-0.7609495</MEAN><ERROR method="simple">0.00033</ERROR></BINNED>
      <BINNED size="256"><COUNT>3232</COUNT><MEAN method="simple">-0.7609495</MEAN><ERROR method="simple">0.000335</ERROR></BINNED>
      <BINNED size="512"><COUNT>1616</COUNT><MEAN method="simple">-0.7609495</MEAN><ERROR method="simple">0.000336</ERROR></BINNED>
      <BINNED size="1024"><COUNT>808</COUNT><MEAN method="simple">-0.7609495</MEAN><ERROR method="simple">0.000327</ERROR></BINNED>
      <BINNED size="2048"><COUNT>404</COUNT><MEAN method="simple">-0.7609495</MEAN><ERROR method="simple">0.000321</ERROR></BINNED>
      <BINNED size="4096"><COUNT>202</COUNT><MEAN method="simple">-0.7609495</MEAN><ERROR method="simple">0.000307</ERROR></BINNED>
    </SCALAR_AVERAGE>
    <SCALAR_AVERAGE name="Energy^2">
      <COUNT>827460</COUNT>
      <MEAN method="simple">2110.021</MEAN>
      <ERROR converged="yes" method="binning">1.63</ERROR>
      <VARIANCE method="simple">2.06e+05</VARIANCE>
      <AUTOCORR method="binning">4.83</AUTOCORR>
      <BINNED size="1"><COUNT>827460</COUNT><MEAN method="simple">2110.021</MEAN><ERROR method="simple">0.499</ERROR></BINNED>
      <BINNED size="2"><COUNT>413730</COUNT><MEAN method="simple">2110.021</MEAN><ERROR method="simple">0.677</ERROR></BINNED>
      <BINNED size="4"><COUNT>206865</COUNT><MEAN method="simple">2110.021</MEAN><ERROR method="simple">0.902</ERROR></BINNED>
      <BINNED size="8"><COUNT>103432</COUNT><MEAN method="simple">2110.018</MEAN><ERROR method="simple">1.16</ERROR></BINNED>
      <BINNED size="16"><COUNT>51716</COUNT><MEAN method="simple">2110.018</MEAN><ERROR method="simple">1.41</ERROR></BINNED>
      <BINNED size="32"><COUNT>25858</COUNT><MEAN method="simple">2110.018</MEAN><ERROR method="simple">1.6</ERROR></BINNED>
      <BINNED size="64"><COUNT>12929</COUNT><MEAN method="simple">2110.018</MEAN><ERROR method="simple">1.7</ERROR></BINNED>
      <BINNED size="128"><COUNT>6464</COUNT><MEAN method="simple">2110.025</MEAN><ERROR method="simple">1.76</ERROR></BINNED>
      <BINNED size="256"><COUNT>3232</COUNT><MEAN method="simple">2110.025</MEAN><ERROR method="simple">1.79</ERROR></BINNED>
      <BINNED size="512"><COUNT>1616</COUNT><MEAN method="simple">2110.025</MEAN><ERROR method="simple">1.8</ERROR></BINNED>
      <BINNED size="1024"><COUNT>808</COUNT><MEAN method="simple">2110.025</MEAN><ERROR method="simple">1.74</ERROR></BINNED>
      <BINNED size="2048"><COUNT>404</COUNT><MEAN method="simple">2110.025</MEAN><ERROR method="simple">1.71</ERROR></BINNED>
      <BINNED size="4096"><COUNT>202</COUNT><MEAN method="simple">2110.025</MEAN><ERROR method="simple">1.63</ERROR></BINNED>
    </SCALAR_AVERAGE>
    <SCALAR_AVERAGE name="Magnetization along Field">
      <COUNT>827460</COUNT>
      <MEAN method="simple">0</MEAN>
      <ERROR converged="yes" method="binning">0</ERROR>
      <VARIANCE method="simple">0</VARIANCE>
      <AUTOCORR method="binning">nan</AUTOCORR>
      <BINNED size="1"><COUNT>827460</COUNT><MEAN method="simple">0</MEAN><ERROR method="simple">0</ERROR></BINNED>
      <BINNED size="2"><COUNT>413730</COUNT><MEAN method="simple">0</MEAN><ERROR method="simple">0</ERROR></BINNED>
      <BINNED size="4"><COUNT>206865</COUNT><MEAN method="simple">0</MEAN><ERROR method="simple">0</ERROR></BINNED>
      <BINNED size="8"><COUNT>103432</COUNT><MEAN method="simple">0</MEAN><ERROR method="simple">0</ERROR></BINNED>
      <BINNED size="16"><COUNT>51716</COUNT><MEAN method="simple">0</MEAN><ERROR method="simple">0</ERROR></BINNED>
      <BINNED size="32"><COUNT>25858</COUNT><MEAN method="simple">0</MEAN><ERROR method="simple">0</ERROR></BINNED>
      <BINNED size="64"><COUNT>12929</COUNT><MEAN method="simple">0</MEAN><ERROR method="simple">0</ERROR></BINNED>
      <BINNED size="128"><COUNT>6464</COUNT><MEAN method="simple">0</MEAN><ERROR method="simple">0</ERROR></BINNED>
      <BINNED size="256"><COUNT>3232</COUNT><MEAN method="simple">0</MEAN><ERROR method="simple">0</ERROR></BINNED>
      <BINNED size="512"><COUNT>1616</COUNT><MEAN method="simple">0</MEAN><ERROR method="simple">0</ERROR></BINNED>
      <BINNED size="1024"><COUNT>808</COUNT><MEAN method="simple">0</MEAN><ERROR method="simple">0</ERROR></BINNED>
      <BINNED size="2048"><COUNT>404</COUNT><MEAN method="simple">0</MEAN><ERROR method="simple">0</ERROR></BINNED>
      <BINNED size="4096"><COUNT>202</COUNT><MEAN method="simple">0</MEAN><ERROR method="simple">0</ERROR></BINNED>
    </SCALAR_AVERAGE>
    <SCALAR_AVERAGE name="Magnetization^2">
      <COUNT>827460</COUNT>
      <MEAN method="simple">0.00227041</MEAN>
      <ERROR converged="yes" method="binning">1.03e-05</ERROR>
      <VARIANCE method="simple">1.09e-05</VARIANCE>
      <AUTOCORR method="binning">3.47</AUTOCORR>
      <BINNED size="1"><COUNT>827460</COUNT><MEAN method="simple">0.00227041</MEAN><ERROR method="simple">3.64e-06</ERROR></BINNED>
      <BINNED size="2"><COUNT>413730</COUNT><MEAN method="simple">0.00227041</MEAN><ERROR method="simple">4.85e-06</ERROR></BINNED>
      <BINNED size="4"><COUNT>206865</COUNT><MEAN method="simple">0.00227041</MEAN><ERROR method="simple">6.32e-06</ERROR></BINNED>
      <BINNED size="8"><COUNT>103432</COUNT><MEAN method="simple">0.00227042</MEAN><ERROR method="simple">7.88e-06</ERROR></BINNED>
      <BINNED size="16"><COUNT>51716</COUNT><MEAN method="simple">0.00227042</MEAN><ERROR method="simple">9.17e-06</ERROR></BINNED>
      <BINNED size="32"><COUNT>25858</COUNT><MEAN method="simple">0.00227042</MEAN><ERROR method="simple">9.98e-06</ERROR></BINNED>
      <BINNED size="64"><COUNT>12929</COUNT><MEAN method="simple">0.00227042</MEAN><ERROR method="simple">1.04e-05</ERROR></BINNED>
      <BINNED size="128"><COUNT>6464</COUNT><MEAN method="simple">0.00227034</MEAN><ERROR method="simple">1.08e-05</ERROR></BINNED>
      <BINNED size="256"><COUNT>3232</COUNT><MEAN method="simple">0.00227034</MEAN><ERROR method="simple">1.09e-05</ERROR></BINNED>
      <BINNED size="512"><COUNT>1616</COUNT><MEAN method="simple">0.00227034</MEAN><ERROR method="simple">1.09e-05</ERROR></BINNED>
      <BINNED size="1024"><COUNT>808</COUNT><MEAN method="simple">0.00227034</MEAN><ERROR method="simple">1.09e-05</ERROR></BINNED>
      <BINNED size="2048"><COUNT>404</COUNT><MEAN method="simple">0.00227034</MEAN><ERROR method="simple">1.07e-05</ERROR></BINNED>
      <BINNED size="4096"><COUNT>202</COUNT><MEAN method="simple">0.00227034</MEAN><ERROR method="simple">1.03e-05</ERROR></BINNED>
    </SCALAR_AVERAGE>
    <SCALAR_AVERAGE name="Staggered Magnetization^2">
      <COUNT>827460</COUNT>
      <MEAN method="simple">0.1231299</MEAN>
      <ERROR converged="yes" method="binning">0.00012</ERROR>
      <VARIANCE method="simple">0.00746</VARIANCE>
      <AUTOCORR method="binning">0.295</AUTOCORR>
      <BINNED size="1"><COUNT>827460</COUNT><MEAN method="simple">0.1231299</MEAN><ERROR method="simple">9.49e-05</ERROR></BINNED>
      <BINNED size="2"><COUNT>413730</COUNT><MEAN method="simple">0.1231299</MEAN><ERROR method="simple">9.84e-05</ERROR></BINNED>
      <BINNED size="4"><COUNT>206865</COUNT><MEAN method="simple">0.1231299</MEAN><ERROR method="simple">0.000103</ERROR></BINNED>
      <BINNED size="8"><COUNT>103432</COUNT><MEAN method="simple">0.1231298</MEAN><ERROR method="simple">0.00011</ERROR></BINNED>
      <BINNED size="16"><COUNT>51716</COUNT><MEAN method="simple">0.1231298</MEAN><ERROR method="simple">0.000116</ERROR></BINNED>
      <BINNED size="32"><COUNT>25858</COUNT><MEAN method="simple">0.1231298</MEAN><ERROR method="simple">0.000121</ERROR></BINNED>
      <BINNED size="64"><COUNT>12929</COUNT><MEAN method="simple">0.12313</MEAN><ERROR method="simple">0.000123</ERROR></BINNED>
      <BINNED size="128"><COUNT>6464</COUNT><MEAN method="simple">0.12313</MEAN><ERROR method="simple">0.000124</ERROR></BINNED>
      <BINNED size="256"><COUNT>3232</COUNT><MEAN method="simple">0.12313</MEAN><ERROR method="simple">0.000124</ERROR></BINNED>
      <BINNED size="512"><COUNT>1616</COUNT><MEAN method="simple">0.1231301</MEAN><ERROR method="simple">0.000123</ERROR></BINNED>
      <BINNED size="1024"><COUNT>808</COUNT><MEAN method="simple">0.1231301</MEAN><ERROR method="simple">0.000122</ERROR></BINNED>
      <BINNED size="2048"><COUNT>404</COUNT><MEAN method="simple">0.1231301</MEAN><ERROR method="simple">0.000117</ERROR></BINNED>
      <BINNED size="4096"><COUNT>202</COUNT><MEAN method="simple">0.1231301</MEAN><ERROR method="simple">0.00012</ERROR></BINNED>
    </SCALAR_AVERAGE>
    <SCALAR_AVERAGE name="Susceptibility">
      <COUNT>827460</COUNT>
      <MEAN method="simple">0.136225</MEAN>
      <ERROR converged="yes" method="binning">0.000615</ERROR>
      <VARIANCE method="simple">0.0394</VARIANCE>
      <AUTOCORR method="binning">3.47</AUTOCORR>
      <BINNED size="1"><COUNT>827460</COUNT><MEAN method="simple">0.136225</MEAN><ERROR method="simple">0.000218</ERROR></BINNED>
      <BINNED size="2"><COUNT>413730</COUNT><MEAN method="simple">0.136225</MEAN><ERROR method="simple">0.000291</ERROR></BINNED>
      <BINNED size="4"><COUNT>206865</COUNT><MEAN method="simple">0.136225</MEAN><ERROR method="simple">0.000379</ERROR></BINNED>
      <BINNED size="8"><COUNT>103432</COUNT><MEAN method="simple">0.136225</MEAN><ERROR method="simple">0.000473</ERROR></BINNED>
      <BINNED size="16"><COUNT>51716</COUNT><MEAN method="simple">0.136225</MEAN><ERROR method="simple">0.00055</ERROR></BINNED>
      <BINNED size="32"><COUNT>25858</COUNT><MEAN method="simple">0.136225</MEAN><ERROR method="simple">0.000599</ERROR></BINNED>
      <BINNED size="64"><COUNT>12929</COUNT><MEAN method="simple">0.136225</MEAN><ERROR method="simple">0.000626</ERROR></BINNED>
      <BINNED size="128"><COUNT>6464</COUNT><MEAN method="simple">0.13622</MEAN><ERROR method="simple">0.000647</ERROR></BINNED>
      <BINNED size="256"><COUNT>3232</COUNT><MEAN method="simple">0.13622</MEAN><ERROR method="simple">0.000653</ERROR></BINNED>
      <BINNED size="512"><COUNT>1616</COUNT><MEAN method="simple">0.13622</MEAN><ERROR method="simple">0.000654</ERROR></BINNED>
      <BINNED size="1024"><COUNT>808</COUNT><MEAN method="simple">0.13622</MEAN><ERROR method="simple">0.000657</ERROR></BINNED>
      <BINNED size="2048"><COUNT>404</COUNT><MEAN method="simple">0.13622</MEAN><ERROR method="simple">0.000642</ERROR></BINNED>
      <BINNED size="4096"><COUNT>202</COUNT><MEAN method="simple">0.13622</MEAN><ERROR method="simple">0.000615</ERROR></BINNED>
    </SCALAR_AVERAGE>
    <SCALAR_AVERAGE name="beta * Energy / sqrt(N)">
      <COUNT>827460</COUNT>
      <MEAN method="simple">-5.894283</MEAN>
      <ERROR converged="yes" method="binning">0.00238</ERROR>
      <VARIANCE method="simple">0.424</VARIANCE>
      <AUTOCORR method="binning">5.03</AUTOCORR>
      <BINNED size="1"><COUNT>827460</COUNT><MEAN method="simple">-5.894283</MEAN><ERROR method="simple">0.000716</ERROR></BINNED>
      <BINNED size="2"><COUNT>413730</COUNT><MEAN method="simple">-5.894283</MEAN><ERROR method="simple">0.000972</ERROR></BINNED>
      <BINNED size="4"><COUNT>206865</COUNT><MEAN method="simple">-5.894283</MEAN><ERROR method="simple">0.0013</ERROR></BINNED>
      <BINNED size="8"><COUNT>103432</COUNT><MEAN method="simple">-5.894279</MEAN><ERROR method="simple">0.00167</ERROR></BINNED>
      <BINNED size="16"><COUNT>51716</COUNT><MEAN method="simple">-5.894279</MEAN><ERROR method="simple">0.00204</ERROR></BINNED>
      <BINNED size="32"><COUNT>25858</COUNT><MEAN method="simple">-5.894279</MEAN><ERROR method="simple">0.00232</ERROR></BINNED>
      <BINNED size="64"><COUNT>12929</COUNT><MEAN method="simple">-5.894279</MEAN><ERROR method="simple">0.00247</ERROR></BINNED>
      <BINNED size="128"><COUNT>6464</COUNT><MEAN method="simple">-5.89429</MEAN><ERROR method="simple">0.00256</ERROR></BINNED>
      <BINNED size="256"><COUNT>3232</COUNT><MEAN method="simple">-5.89429</MEAN><ERROR method="simple">0.00259</ERROR></BINNED>
      <BINNED size="512"><COUNT>1616</COUNT><MEAN method="simple">-5.89429</MEAN><ERROR method="simple">0.00261</ERROR></BINNED>
      <BINNED size="1024"><COUNT>808</COUNT><MEAN method="simple">-5.89429</MEAN><ERROR method="simple">0.00253</ERROR></BINNED>
      <BINNED size="2048"><COUNT>404</COUNT><MEAN method="simple">-5.89429</MEAN><ERROR method="simple">0.00248</ERROR></BINNED>
      <BINNED size="4096"><COUNT>202</COUNT><MEAN method="simple">-5.89429</MEAN><ERROR method="simple">0.00238</ERROR></BINNED>
    </SCALAR_AVERAGE>
    <SCALAR_AVERAGE name="|Magnetization|">
      <COUNT>827460</COUNT>
      <MEAN method="simple">0.0362195</MEAN>
      <ERROR converged="yes" method="binning">8.64e-05</ERROR>
      <VARIANCE method="simple">0.000959</VARIANCE>
      <AUTOCORR method="binning">2.72</AUTOCORR>
      <BINNED size="1"><COUNT>827460</COUNT><MEAN method="simple">0.03621947</MEAN><ERROR method="simple">3.4e-05</ERROR></BINNED>
      <BINNED size="2"><COUNT>413730</COUNT><MEAN method="simple">0.0362195</MEAN><ERROR method="simple">4.44e-05</ERROR></BINNED>
      <BINNED size="4"><COUNT>206865</COUNT><MEAN method="simple">0.0362195</MEAN><ERROR method="simple">5.69e-05</ERROR></BINNED>
      <BINNED size="8"><COUNT>103432</COUNT><MEAN method="simple">0.0362195</MEAN><ERROR method="simple">6.96e-05</ERROR></BINNED>
      <BINNED size="16"><COUNT>51716</COUNT><MEAN method="simple">0.0362195</MEAN><ERROR method="simple">8e-05</ERROR></BINNED>
      <BINNED size="32"><COUNT>25858</COUNT><MEAN method="simple">0.0362195</MEAN><ERROR method="simple">8.64e-05</ERROR></BINNED>
      <BINNED size="64"><COUNT>12929</COUNT><MEAN method="simple">0.0362195</MEAN><ERROR method="simple">9.01e-05</ERROR></BINNED>
      <BINNED size="128"><COUNT>6464</COUNT><MEAN method="simple">0.0362186</MEAN><ERROR method="simple">9.28e-05</ERROR></BINNED>
      <BINNED size="256"><COUNT>3232</COUNT><MEAN method="simple">0.0362186</MEAN><ERROR method="simple">9.4e-05</ERROR></BINNED>
      <BINNED size="512"><COUNT>1616</COUNT><MEAN method="simple">0.0362186</MEAN><ERROR method="simple">9.43e-05</ERROR></BINNED>
      <BINNED size="1024"><COUNT>808</COUNT><MEAN method="simple">0.0362186</MEAN><ERROR method="simple">9.33e-05</ERROR></BINNED>
      <BINNED size="2048"><COUNT>404</COUNT><MEAN method="simple">0.0362186</MEAN><ERROR method="simple">9.03e-05</ERROR></BINNED>
      <BINNED size="4096"><COUNT>202</COUNT><MEAN method="simple">0.0362186</MEAN><ERROR method="simple">8.64e-05</ERROR></BINNED>
    </SCALAR_AVERAGE>
    <SCALAR_AVERAGE name="|Staggered Magnetization|">
      <COUNT>827460</COUNT>
      <MEAN method="simple">0.284317</MEAN>
      <ERROR converged="yes" method="binning">0.000333</ERROR>
      <VARIANCE method="simple">0.0422</VARIANCE>
      <AUTOCORR method="binning">0.584</AUTOCORR>
      <BINNED size="1"><COUNT>827460</COUNT><MEAN method="simple">0.2843168</MEAN><ERROR method="simple">0.000226</ERROR></BINNED>
      <BINNED size="2"><COUNT>413730</COUNT><MEAN method="simple">0.2843168</MEAN><ERROR method="simple">0.000262</ERROR></BINNED>
      <BINNED size="4"><COUNT>206865</COUNT><MEAN method="simple">0.284317</MEAN><ERROR method="simple">0.000295</ERROR></BINNED>
      <BINNED size="8"><COUNT>103432</COUNT><MEAN method="simple">0.284317</MEAN><ERROR method="simple">0.00032</ERROR></BINNED>
      <BINNED size="16"><COUNT>51716</COUNT><MEAN method="simple">0.284317</MEAN><ERROR method="simple">0.000337</ERROR></BINNED>
      <BINNED size="32"><COUNT>25858</COUNT><MEAN method="simple">0.284317</MEAN><ERROR method="simple">0.000346</ERROR></BINNED>
      <BINNED size="64"><COUNT>12929</COUNT><MEAN method="simple">0.284317</MEAN><ERROR method="simple">0.000351</ERROR></BINNED>
      <BINNED size="128"><COUNT>6464</COUNT><MEAN method="simple">0.284318</MEAN><ERROR method="simple">0.000356</ERROR></BINNED>
      <BINNED size="256"><COUNT>3232</COUNT><MEAN method="simple">0.284318</MEAN><ERROR method="simple">0.000361</ERROR></BINNED>
      <BINNED size="512"><COUNT>1616</COUNT><MEAN method="simple">0.284318</MEAN><ERROR method="simple">0.000352</ERROR></BINNED>
      <BINNED size="1024"><COUNT>808</COUNT><MEAN method="simple">0.284318</MEAN><ERROR method="simple">0.000357</ERROR></BINNED>
      <BINNED size="2048"><COUNT>404</COUNT><MEAN method="simple">0.284318</MEAN><ERROR method="simple">0.000342</ERROR></BINNED>
      <BINNED size="4096"><COUNT>202</COUNT><MEAN method="simple">0.284318</MEAN><ERROR method="simple">0.000333</ERROR></BINNED>
    </SCALAR_AVERAGE>
  </AVERAGES>
  <MCRUN>
    <EXECUTED phase="equilibrating">
      <FROM>2009-Oct-31 22:13:45</FROM>
      <TO>2009-Oct-31 22:13:45</TO>
      <MACHINE><NAME>powerbook-troyer.local</NAME></MACHINE>
    </EXECUTED>
    <EXECUTED phase="running">
      <FROM>2009-Oct-31 22:13:45</FROM>
      <TO>2009-Oct-31 22:13:58</TO>
      <MACHINE><NAME>powerbook-troyer.local</NAME></MACHINE>
    </EXECUTED>
    <CHECKPOINT format="osiris" file="classical2a.task11.out.run1"/>
  </MCRUN>
</SIMULATION>
